cronpulse/__init__.py
cronpulse/monitor.py
cronpulse-0.3.1.dist-info/METADATA
cronpulse-0.3.1.dist-info/WHEEL
cronpulse-0.3.1.dist-info/top_level.txt
cronpulse-0.3.1.dist-info/RECORD
