Metadata-Version: 2.1
Name: cronpulse
Version: 0.3.1
Summary: A simple monitor and wrap function for cron jobs
Home-page: https://github.com/cronpulse-live/cronpulse-python.git
Author: Amr Sobhy
Author-email: team@cronpulse.live
Classifier: Programming Language :: Python :: 3
Classifier: License :: OSI Approved :: MIT License
Classifier: Operating System :: OS Independent
Requires-Python: >=3.6
Requires-Dist: requests
